app/__init__.py
app/api_key.py
app/app.py
app/commit_msg.py
app/groq_api_key.py
app/groq_generator.py
app/llm.py
app/ollama_generator.py
app/system_prompt.py
icommit-0.3.0.dist-info/METADATA
icommit-0.3.0.dist-info/WHEEL
icommit-0.3.0.dist-info/entry_points.txt
icommit-0.3.0.dist-info/top_level.txt
icommit-0.3.0.dist-info/RECORD
