Metadata-Version: 2.4
Name: icommit
Version: 0.3.0
Summary: A CLI tool to generate commit messages from your code changes
Home-page: https://github.com/OMAR-AHMED-SAAD/icommit
Author: Omar Ahmed Saad
Author-email: omarahmedaww@gmail.com
License: MIT
Classifier: License :: OSI Approved :: MIT License
Classifier: Programming Language :: Python :: 3.11
Classifier: Operating System :: OS Independent
Requires-Python: >=3.9
Requires-Dist: groq>=0.15.0
Requires-Dist: pyperclip>=1.9.0
Requires-Dist: colorama>=0.4.6
Requires-Dist: ollama>=0.4.8
Provides-Extra: dev
Requires-Dist: twine>=6.1.0; extra == "dev"
Dynamic: author
Dynamic: author-email
Dynamic: classifier
Dynamic: description
Dynamic: description-content-type
Dynamic: home-page
Dynamic: license
Dynamic: provides-extra
Dynamic: requires-dist
Dynamic: requires-python
Dynamic: summary
